exrio-0.2.0.dist-info/METADATA
exrio-0.2.0.dist-info/WHEEL
exrio/image.py
exrio/__init__.py
exrio/py.typed
exrio/_rust.abi3.so
exrio-0.2.0.dist-info/RECORD
