Metadata-Version: 2.4
Name: exrio
Version: 0.2.0
Requires-Dist: numpy <2
Summary: Read and write OpenEXR files in Python with no system dependencies.
Requires-Python: >=3.9
